{"cameraMode":{"drawMode":0,"name":"Shaded","section":"Shading Mode"},"sceneLighting":true,"audioPlay":false,"sceneViewState":{"m_AlwaysRefresh":false,"showFog":true,"showSkybox":true,"showFlares":true,"showImageEffects":true,"showParticleSystems":true,"showVisualEffectGraphs":true,"m_FxEnabled":true},"in2DMode":false,"pivot":{"x":2.09445858001709,"y":14.556294441223145,"z":-16.27475357055664},"rotation":{"x":-0.28135186433792117,"y":-0.028515584766864778,"z":0.008357172831892968,"w":-0.9592210650444031},"size":2.598076105117798,"orthographic":false}